lgbn/__init__.py
lgbn/estimators.py
lgbn/models.py
lgbn/scores.py
lgbn-0.1.2.dist-info/LICENSE
lgbn-0.1.2.dist-info/METADATA
lgbn-0.1.2.dist-info/WHEEL
lgbn-0.1.2.dist-info/top_level.txt
lgbn-0.1.2.dist-info/RECORD
