Metadata-Version: 2.1
Name: lgbn
Version: 0.1.2
Summary: Structure and parameter learning for linear Gaussian Bayesian networks.
Home-page: https://github.com/knifecake/lgbn
Author: Elias Hernandis
Author-email: elias@hernandis.me
Project-URL: Bug Tracker, https://github.com/knifecake/lgbn/issues
Project-URL: Documentation, https://lgbn.readthedocs.io/en/latest/
Classifier: Programming Language :: Python :: 3
Classifier: Programming Language :: Python :: 3.9
Classifier: Programming Language :: Python :: 3 :: Only
Classifier: License :: OSI Approved :: MIT License
Classifier: Operating System :: OS Independent
Requires-Python: >=3.9
License-File: LICENSE
Requires-Dist: scipy (>=1.8)
Requires-Dist: networkx (>=2.8)
Requires-Dist: pandas (>=1.4)
Requires-Dist: scikit-learn (>=1.1)
